{"response": {"status": {"version": "4.2", "code": 0, "message": "Success"}, "songs": [{"title": "Can't Feel My Face", "artist_name": "The Weeknd", "artist_foreign_ids": [{"catalog": "7digital-US", "foreign_id": "7digital-US:artist:1420335"}], "tracks": [], "song_hotttnesss": 0.721485, "artist_id": "ARYUDWF12F2B89BB33", "id": "SOMVZDS14DDE5909E7"}, {"title": "Stole the Show", "artist_name": "Kygo", "artist_foreign_ids": [{"catalog": "7digital-US", "foreign_id": "7digital-US:artist:1895765"}], "tracks": [], "song_hotttnesss": 0.698138, "artist_id": "ARTZYQN13EEEF973E7", "id": "SOJJAOR14C0CA2A061"}, {"title": "Stole The Show", "artist_name": "Kygo", "artist_foreign_ids": [{"catalog": "7digital-US", "foreign_id": "7digital-US:artist:1895765"}], "tracks": [], "song_hotttnesss": 0.698138, "artist_id": "ARTZYQN13EEEF973E7", "id": "SOJKYVE14D8887B195"}, {"title": "Trap Queen", "artist_name": "Fetty Wap", "artist_foreign_ids": [{"catalog": "7digital-US", "foreign_id": "7digital-US:artist:2278920"}], "tracks": [], "song_hotttnesss": 0.693684, "artist_id": "ARXCQFR14690BA8487", "id": "SOMUJMK14A45DF92E3"}, {"title": "Trap Queen (feat. Azealia Banks, Quavo & Gucci Mane)", "artist_name": "Fetty Wap", "artist_foreign_ids": [{"catalog": "7digital-US", "foreign_id": "7digital-US:artist:2278920"}], "tracks": [], "song_hotttnesss": 0.693684, "artist_id": "ARXCQFR14690BA8487", "id": "SOJECCD14D1A8E725F"}, {"title": "Trap Queen (feat. Quavo & Gucci Mane)", "artist_name": "Fetty Wap", "artist_foreign_ids": [{"catalog": "7digital-US", "foreign_id": "7digital-US:artist:2278920"}], "tracks": [], "song_hotttnesss": 0.693684, "artist_id": "ARXCQFR14690BA8487", "id": "SOWWHPZ14D1A8E1FEA"}, {"title": "Trap Queen", "artist_name": "Fetty Wap", "artist_foreign_ids": [{"catalog": "7digital-US", "foreign_id": "7digital-US:artist:2278920"}], "tracks": [], "song_hotttnesss": 0.693684, "artist_id": "ARXCQFR14690BA8487", "id": "SOKSDPR14BC8FB87E4"}, {"title": "Trap Queen", "artist_name": "Fetty Wap", "artist_foreign_ids": [{"catalog": "7digital-US", "foreign_id": "7digital-US:artist:2278920"}], "tracks": [], "song_hotttnesss": 0.693684, "artist_id": "ARXCQFR14690BA8487", "id": "SOEVUXS14A45E03318"}, {"title": "Trap Queen", "artist_name": "Fetty Wap", "artist_foreign_ids": [{"catalog": "7digital-US", "foreign_id": "7digital-US:artist:2278920"}], "tracks": [], "song_hotttnesss": 0.693684, "artist_id": "ARXCQFR14690BA8487", "id": "SOOJPEF14B5CE08101"}, {"title": "Good For You", "artist_name": "Selena Gomez", "artist_foreign_ids": [{"catalog": "7digital-US", "foreign_id": "7digital-US:artist:298887"}], "tracks": [], "song_hotttnesss": 0.691108, "artist_id": "ARZ5NER11A348F0B33", "id": "SOCBSXB14E1DFC4C75"}, {"title": "Ain't Nobody (Loves Me Better)", "artist_name": "Felix Jaehn", "artist_foreign_ids": [{"catalog": "7digital-US", "foreign_id": "7digital-US:artist:1985097"}], "tracks": [], "song_hotttnesss": 0.686353, "artist_id": "ARFCEEW140A1ED1875", "id": "SOJZMNP14EDD1C4E36"}, {"title": "Ain't Nobody (Loves Me Better)", "artist_name": "Felix Jaehn", "artist_foreign_ids": [{"catalog": "7digital-US", "foreign_id": "7digital-US:artist:1985097"}], "tracks": [], "song_hotttnesss": 0.686353, "artist_id": "ARFCEEW140A1ED1875", "id": "SOZOIDR14C02B654D4"}, {"title": "Firestone", "artist_name": "Kygo", "artist_foreign_ids": [{"catalog": "7digital-US", "foreign_id": "7digital-US:artist:1895765"}], "tracks": [], "song_hotttnesss": 0.684706, "artist_id": "ARTZYQN13EEEF973E7", "id": "SOTCKGT14A08A2C485"}, {"title": "Firestone", "artist_name": "Kygo", "artist_foreign_ids": [{"catalog": "7digital-US", "foreign_id": "7digital-US:artist:1895765"}], "tracks": [], "song_hotttnesss": 0.684706, "artist_id": "ARTZYQN13EEEF973E7", "id": "SOCWAHT149FB948412"}, {"title": "Firestone (feat. Conrad Sewell)", "artist_name": "Kygo", "artist_foreign_ids": [{"catalog": "7digital-US", "foreign_id": "7digital-US:artist:1895765"}], "tracks": [], "song_hotttnesss": 0.684706, "artist_id": "ARTZYQN13EEEF973E7", "id": "SOBERNG14CF52971BC"}, {"title": "Firestone", "artist_name": "Kygo", "artist_foreign_ids": [{"catalog": "7digital-US", "foreign_id": "7digital-US:artist:1895765"}], "tracks": [], "song_hotttnesss": 0.684706, "artist_id": "ARTZYQN13EEEF973E7", "id": "SOFIFKV14DF5E77E24"}, {"title": "Firestone", "artist_name": "Kygo", "artist_foreign_ids": [{"catalog": "7digital-US", "foreign_id": "7digital-US:artist:1895765"}], "tracks": [], "song_hotttnesss": 0.684706, "artist_id": "ARTZYQN13EEEF973E7", "id": "SOYHHND14DE57D61E4"}, {"title": "Firestone", "artist_name": "Kygo", "artist_foreign_ids": [{"catalog": "7digital-US", "foreign_id": "7digital-US:artist:1895765"}], "tracks": [], "song_hotttnesss": 0.684706, "artist_id": "ARTZYQN13EEEF973E7", "id": "SOABNBF14D9C91C60D"}, {"title": "Hold My Hand", "artist_name": "Jess Glynne", "tracks": [], "song_hotttnesss": 0.670535, "artist_id": "ARDVNQH14408EC0258", "id": "SODFAJT14C029F95EE"}, {"title": "Hold My Hand", "artist_name": "Jess Glynne", "tracks": [], "song_hotttnesss": 0.670535, "artist_id": "ARDVNQH14408EC0258", "id": "SOEWNPH14EE975944E"}, {"title": "Runaway (U & I)", "artist_name": "Galantis", "artist_foreign_ids": [{"catalog": "7digital-US", "foreign_id": "7digital-US:artist:1355525"}], "tracks": [], "song_hotttnesss": 0.669319, "artist_id": "ARFKZRQ1391FF1B17F", "id": "SONYNFW14B97A499B4"}, {"title": "Runaway (U & I)", "artist_name": "Galantis", "artist_foreign_ids": [{"catalog": "7digital-US", "foreign_id": "7digital-US:artist:1355525"}], "tracks": [], "song_hotttnesss": 0.669319, "artist_id": "ARFKZRQ1391FF1B17F", "id": "SOKBJJQ14EE974D4A1"}, {"title": "Runaway (U & I)", "artist_name": "Galantis", "artist_foreign_ids": [{"catalog": "7digital-US", "foreign_id": "7digital-US:artist:1355525"}], "tracks": [], "song_hotttnesss": 0.669319, "artist_id": "ARFKZRQ1391FF1B17F", "id": "SOGCHAZ14A43FEF634"}, {"title": "The Hills", "artist_name": "The Weeknd", "artist_foreign_ids": [{"catalog": "7digital-US", "foreign_id": "7digital-US:artist:1420335"}], "tracks": [], "song_hotttnesss": 0.667648, "artist_id": "ARYUDWF12F2B89BB33", "id": "SOEOUMQ14D9E425665"}, {"title": "Stolen Dance", "artist_name": "Milky Chance", "artist_foreign_ids": [{"catalog": "7digital-US", "foreign_id": "7digital-US:artist:1522434"}], "tracks": [], "song_hotttnesss": 0.663686, "artist_id": "ARMDNNP13D610B088F", "id": "SODEJCG14602A5ECC7"}, {"title": "Stolen Dance", "artist_name": "Milky Chance", "artist_foreign_ids": [{"catalog": "7digital-US", "foreign_id": "7digital-US:artist:1522434"}], "tracks": [], "song_hotttnesss": 0.663686, "artist_id": "ARMDNNP13D610B088F", "id": "SOQYYMY147E7F079DE"}, {"title": "Stolen Dance", "artist_name": "Milky Chance", "artist_foreign_ids": [{"catalog": "7digital-US", "foreign_id": "7digital-US:artist:1522434"}], "tracks": [], "song_hotttnesss": 0.663686, "artist_id": "ARMDNNP13D610B088F", "id": "SOQKHVU146528F521B"}, {"title": "Stolen Dance", "artist_name": "Milky Chance", "artist_foreign_ids": [{"catalog": "7digital-US", "foreign_id": "7digital-US:artist:1522434"}], "tracks": [], "song_hotttnesss": 0.663686, "artist_id": "ARMDNNP13D610B088F", "id": "SOFNCMG143B391FCE0"}, {"title": "Stolen Dance", "artist_name": "Milky Chance", "artist_foreign_ids": [{"catalog": "7digital-US", "foreign_id": "7digital-US:artist:1522434"}], "tracks": [], "song_hotttnesss": 0.663686, "artist_id": "ARMDNNP13D610B088F", "id": "SOVHLNR14602AD914B"}, {"title": "Stolen Dance", "artist_name": "Milky Chance", "artist_foreign_ids": [{"catalog": "7digital-US", "foreign_id": "7digital-US:artist:1522434"}], "tracks": [], "song_hotttnesss": 0.663686, "artist_id": "ARMDNNP13D610B088F", "id": "SOCENJR142C425B63B"}, {"title": "Somebody", "artist_name": "Natalie La Rose", "tracks": [], "song_hotttnesss": 0.654476, "artist_id": "ARJIZBK14A457100AF", "id": "SONYFHY14B66F2D36C"}, {"title": "Don't Look Down", "artist_name": "Martin Garrix", "artist_foreign_ids": [{"catalog": "7digital-US", "foreign_id": "7digital-US:artist:1390159"}], "tracks": [], "song_hotttnesss": 0.652877, "artist_id": "ARAGGUA136E57105F8", "id": "SOGGMYF14DD9257D4B"}, {"title": "Don't Look Down", "artist_name": "Martin Garrix", "artist_foreign_ids": [{"catalog": "7digital-US", "foreign_id": "7digital-US:artist:1390159"}], "tracks": [], "song_hotttnesss": 0.652877, "artist_id": "ARAGGUA136E57105F8", "id": "SOKOLKP14C1638CC3D"}, {"title": "Rude", "artist_name": "Magic!", "artist_foreign_ids": [{"catalog": "7digital-US", "foreign_id": "7digital-US:artist:2040858"}], "tracks": [{"release_image": "http://artwork-cdn.7static.com/static/img/sleeveart/00/030/284/0003028406_200.jpg", "foreign_release_id": "7digital-US:release:3028406", "preview_url": "http://previews.7digital.com/clip/32296587", "catalog": "7digital-US", "foreign_id": "7digital-US:track:32296587", "id": "TRQSPSX141F210F886"}, {"release_image": "http://artwork-cdn.7static.com/static/img/sleeveart/00/035/918/0003591833_200.jpg", "foreign_release_id": "7digital-US:release:3591833", "preview_url": "http://previews.7digital.com/clip/37707442", "catalog": "7digital-US", "foreign_id": "7digital-US:track:37707442", "id": "TRWJJRQ1475F44631A"}], "song_hotttnesss": 0.646521, "artist_id": "ARYUWLF1473F667067", "id": "SOJOAOT1458B54F8BC"}, {"title": "Heroes", "artist_name": "Måns Zelmerlöw", "artist_foreign_ids": [{"catalog": "7digital-US", "foreign_id": "7digital-US:artist:98978"}], "tracks": [], "song_hotttnesss": 0.646102, "artist_id": "ARLSB9Q1187B9B8D62", "id": "SOBKQFT14BAA49549B"}, {"title": "Bills", "artist_name": "Lunchmoney Lewis", "tracks": [], "song_hotttnesss": 0.64358, "artist_id": "ARIYYFR14B5A84137A", "id": "SOSXYUI14B5CF14B35"}, {"title": "Heroes (We Could Be)", "artist_name": "Alesso", "artist_foreign_ids": [{"catalog": "7digital-US", "foreign_id": "7digital-US:artist:936586"}], "tracks": [], "song_hotttnesss": 0.641346, "artist_id": "ARFBFYB12C60E4E610", "id": "SOOPQDL14E88891878"}, {"title": "Heroes (we could be)", "artist_name": "Alesso", "artist_foreign_ids": [{"catalog": "7digital-US", "foreign_id": "7digital-US:artist:936586"}], "tracks": [], "song_hotttnesss": 0.641346, "artist_id": "ARFBFYB12C60E4E610", "id": "SOXWUBA14CF565B7A0"}, {"title": "Heroes (We Could Be)", "artist_name": "Alesso", "artist_foreign_ids": [{"catalog": "7digital-US", "foreign_id": "7digital-US:artist:936586"}], "tracks": [], "song_hotttnesss": 0.641346, "artist_id": "ARFBFYB12C60E4E610", "id": "SOCYEJH14870099496"}, {"title": "Peanut Butter Jelly", "artist_name": "Galantis", "artist_foreign_ids": [{"catalog": "7digital-US", "foreign_id": "7digital-US:artist:1355525"}], "tracks": [], "song_hotttnesss": 0.640028, "artist_id": "ARFKZRQ1391FF1B17F", "id": "SOBAOTM14F374E83FE"}, {"title": "Peanut Butter Jelly", "artist_name": "Galantis", "artist_foreign_ids": [{"catalog": "7digital-US", "foreign_id": "7digital-US:artist:1355525"}], "tracks": [], "song_hotttnesss": 0.640028, "artist_id": "ARFKZRQ1391FF1B17F", "id": "SOWKEYM14C890C194B"}, {"title": "Norf Norf", "artist_name": "Vince Staples", "artist_foreign_ids": [{"catalog": "7digital-US", "foreign_id": "7digital-US:artist:1408860"}], "tracks": [], "song_hotttnesss": 0.621392, "artist_id": "ARKFMFQ13A6C1556A1", "id": "SORZXIJ14DEDEEC2F3"}, {"title": "Secrets - Radio Edit", "artist_name": "Tiësto", "artist_foreign_ids": [{"catalog": "7digital-US", "foreign_id": "7digital-US:artist:8669"}], "tracks": [], "song_hotttnesss": 0.620457, "artist_id": "ARIW30O1187FB5A29A", "id": "SOZIJAG14C2B1B0DEF"}, {"title": "Watch Me (Whip / Nae Nae)", "artist_name": "Silento", "tracks": [], "song_hotttnesss": 0.617619, "artist_id": "ARQLUKU14A3B1DDF99", "id": "SOGGAVF14F3D6AD0E9"}, {"title": "Watch Me (Whip / Nae Nae)", "artist_name": "Silento", "tracks": [], "song_hotttnesss": 0.617619, "artist_id": "ARQLUKU14A3B1DDF99", "id": "SOFVATN14E7791BA21"}, {"title": "Old Thing Back", "artist_name": "Matoma", "tracks": [], "song_hotttnesss": 0.616412, "artist_id": "ARJOEQN148D6F2A0D6", "id": "SOXNCKB14DA0BAC8DD"}, {"title": "Old Thing Back (feat. Ja Rule and Ralph Tresvant)", "artist_name": "Matoma", "tracks": [], "song_hotttnesss": 0.616412, "artist_id": "ARJOEQN148D6F2A0D6", "id": "SOHZQQW14B4825EAA9"}, {"title": "Nasty Freestyle", "artist_name": "T-Wayne", "artist_foreign_ids": [{"catalog": "7digital-US", "foreign_id": "7digital-US:artist:2065672"}], "tracks": [], "song_hotttnesss": 0.613915, "artist_id": "ARKVQHP1269FB26ACF", "id": "SOQAZLZ14D5B0D30CC"}, {"title": "Nasty Freestyle", "artist_name": "T-Wayne", "artist_foreign_ids": [{"catalog": "7digital-US", "foreign_id": "7digital-US:artist:2065672"}], "tracks": [], "song_hotttnesss": 0.613915, "artist_id": "ARKVQHP1269FB26ACF", "id": "SOCVNGM14C77FA6884"}, {"title": "Nasty Freestyle", "artist_name": "T-Wayne", "artist_foreign_ids": [{"catalog": "7digital-US", "foreign_id": "7digital-US:artist:2065672"}], "tracks": [], "song_hotttnesss": 0.613915, "artist_id": "ARKVQHP1269FB26ACF", "id": "SOLVCJC14C0D53AE51"}, {"title": "I'm an Albatraoz", "artist_name": "AronChupa", "artist_foreign_ids": [{"catalog": "7digital-US", "foreign_id": "7digital-US:artist:2103393"}], "tracks": [{"release_image": "http://artwork-cdn.7static.com/static/img/sleeveart/00/033/951/0003395147_200.jpg", "foreign_release_id": "7digital-US:release:3395147", "preview_url": "http://previews.7digital.com/clip/35793994", "catalog": "7digital-US", "foreign_id": "7digital-US:track:35793994", "id": "TRBGHOK14567F9C9EB"}], "song_hotttnesss": 0.613678, "artist_id": "ARGYKIB142EE80AF67", "id": "SOFAGCS145223F8095"}, {"title": "Faded", "artist_name": "Zhu", "artist_foreign_ids": [{"catalog": "7digital-US", "foreign_id": "7digital-US:artist:297899"}], "tracks": [], "song_hotttnesss": 0.607648, "artist_id": "ARZLHMW12AF7DABF36", "id": "SOISTOY14D543739EE"}, {"title": "Faded", "artist_name": "Zhu", "artist_foreign_ids": [{"catalog": "7digital-US", "foreign_id": "7digital-US:artist:297899"}], "tracks": [], "song_hotttnesss": 0.607648, "artist_id": "ARZLHMW12AF7DABF36", "id": "SOOENRW1495F2A8B95"}, {"title": "Faded", "artist_name": "Zhu", "artist_foreign_ids": [{"catalog": "7digital-US", "foreign_id": "7digital-US:artist:297899"}], "tracks": [], "song_hotttnesss": 0.607648, "artist_id": "ARZLHMW12AF7DABF36", "id": "SOPAFGS146565B2017"}, {"title": "Faded", "artist_name": "Zhu", "artist_foreign_ids": [{"catalog": "7digital-US", "foreign_id": "7digital-US:artist:297899"}], "tracks": [], "song_hotttnesss": 0.607648, "artist_id": "ARZLHMW12AF7DABF36", "id": "SOPZGBB146F9405C98"}, {"title": "Faded", "artist_name": "Zhu", "artist_foreign_ids": [{"catalog": "7digital-US", "foreign_id": "7digital-US:artist:297899"}], "tracks": [], "song_hotttnesss": 0.607648, "artist_id": "ARZLHMW12AF7DABF36", "id": "SOFMCTU14A5954BCD7"}, {"title": "Goodbye (feat. Lyse) [Radio Edit]", "artist_name": "Feder", "artist_foreign_ids": [{"catalog": "7digital-US", "foreign_id": "7digital-US:artist:1468029"}], "tracks": [], "song_hotttnesss": 0.607633, "artist_id": "ARBUOJU13361805FF0", "id": "SOCSFQV14A8A42F320"}, {"title": "Next To Me", "artist_name": "Otto Knows", "artist_foreign_ids": [{"catalog": "7digital-US", "foreign_id": "7digital-US:artist:1256682"}], "tracks": [], "song_hotttnesss": 0.599158, "artist_id": "ARYUPIQ131AAE260D1", "id": "SOSPOLZ14D0A5448A4"}, {"title": "Next To Me", "artist_name": "Otto Knows", "artist_foreign_ids": [{"catalog": "7digital-US", "foreign_id": "7digital-US:artist:1256682"}], "tracks": [], "song_hotttnesss": 0.599158, "artist_id": "ARYUPIQ131AAE260D1", "id": "SOKNCGT14D57BDEB34"}, {"title": "Save Me", "artist_name": "LISTENBEE", "tracks": [], "song_hotttnesss": 0.598859, "artist_id": "ARXJGER14A7AC2F41C", "id": "SOAYTBL14A9474B816"}, {"title": "Lift Me Up", "artist_name": "Vince Staples", "artist_foreign_ids": [{"catalog": "7digital-US", "foreign_id": "7digital-US:artist:1408860"}], "tracks": [], "song_hotttnesss": 0.598284, "artist_id": "ARKFMFQ13A6C1556A1", "id": "SOANZXK14E28529A14"}, {"title": "Something About You", "artist_name": "Hayden James", "artist_foreign_ids": [{"catalog": "7digital-US", "foreign_id": "7digital-US:artist:1538546"}], "tracks": [], "song_hotttnesss": 0.596546, "artist_id": "ARQAYFF12D5CD7AB3A", "id": "SOBYCYF14A457144E0"}, {"title": "Something About You", "artist_name": "Hayden James", "artist_foreign_ids": [{"catalog": "7digital-US", "foreign_id": "7digital-US:artist:1538546"}], "tracks": [], "song_hotttnesss": 0.596546, "artist_id": "ARQAYFF12D5CD7AB3A", "id": "SOWOJXL14CE49B791D"}, {"title": "Something About You", "artist_name": "Hayden James", "artist_foreign_ids": [{"catalog": "7digital-US", "foreign_id": "7digital-US:artist:1538546"}], "tracks": [], "song_hotttnesss": 0.596546, "artist_id": "ARQAYFF12D5CD7AB3A", "id": "SOYXJOV14E8889A296"}, {"title": "Something About You", "artist_name": "Hayden James", "artist_foreign_ids": [{"catalog": "7digital-US", "foreign_id": "7digital-US:artist:1538546"}], "tracks": [], "song_hotttnesss": 0.596546, "artist_id": "ARQAYFF12D5CD7AB3A", "id": "SOECHUI14DA5CCCE09"}, {"title": "Shots & Squats", "artist_name": "Vigiland", "tracks": [], "song_hotttnesss": 0.59265, "artist_id": "ARFSXOZ14185A12FF9", "id": "SOHQZKB14DD1695AA2"}, {"title": "Five More Hours", "artist_name": "Deorro", "artist_foreign_ids": [{"catalog": "7digital-US", "foreign_id": "7digital-US:artist:1356962"}], "tracks": [], "song_hotttnesss": 0.590055, "artist_id": "ARSVRID139A2DB2C5B", "id": "SOQNFLC14C0282740A"}, {"title": "Five More Hours", "artist_name": "Deorro", "artist_foreign_ids": [{"catalog": "7digital-US", "foreign_id": "7digital-US:artist:1356962"}], "tracks": [], "song_hotttnesss": 0.590055, "artist_id": "ARSVRID139A2DB2C5B", "id": "SOSSNNK14F9EA797B4"}, {"title": "679 (feat. Remy Boyz)", "artist_name": "Fetty Wap", "artist_foreign_ids": [{"catalog": "7digital-US", "foreign_id": "7digital-US:artist:2278920"}], "tracks": [], "song_hotttnesss": 0.589691, "artist_id": "ARXCQFR14690BA8487", "id": "SOBHRJZ14E64A69F56"}, {"title": "Cool", "artist_name": "Alesso", "artist_foreign_ids": [{"catalog": "7digital-US", "foreign_id": "7digital-US:artist:936586"}], "tracks": [], "song_hotttnesss": 0.588645, "artist_id": "ARFBFYB12C60E4E610", "id": "SOEBFGM14B80D22A0D"}, {"title": "Cool", "artist_name": "Alesso", "artist_foreign_ids": [{"catalog": "7digital-US", "foreign_id": "7digital-US:artist:936586"}], "tracks": [], "song_hotttnesss": 0.588645, "artist_id": "ARFBFYB12C60E4E610", "id": "SOPLBSY14B9A7D420C"}, {"title": "Cool", "artist_name": "Alesso", "artist_foreign_ids": [{"catalog": "7digital-US", "foreign_id": "7digital-US:artist:936586"}], "tracks": [], "song_hotttnesss": 0.588645, "artist_id": "ARFBFYB12C60E4E610", "id": "SOSFZAC14ED8033C69"}, {"title": "Do You Remember", "artist_name": "Jarryd James", "tracks": [], "song_hotttnesss": 0.585185, "artist_id": "ARUZPAG14B79590666", "id": "SOQMQUD14B7C8624B4"}, {"title": "Señorita", "artist_name": "Vince Staples", "artist_foreign_ids": [{"catalog": "7digital-US", "foreign_id": "7digital-US:artist:1408860"}], "tracks": [], "song_hotttnesss": 0.584285, "artist_id": "ARKFMFQ13A6C1556A1", "id": "SOPSDUC14D88CB0B5F"}, {"title": "Just Give Me a Reason", "artist_name": "P!nk", "artist_foreign_ids": [{"catalog": "7digital-US", "foreign_id": "7digital-US:artist:226"}], "tracks": [{"album_type": "other", "release_image": "http://artwork-cdn.7static.com/static/img/sleeveart/00/027/041/0002704139_200.jpg", "album_date": "2013-05-07", "foreign_release_id": "7digital-US:release:2704139", "preview_url": "http://previews.7digital.com/clip/29060435", "catalog": "7digital-US", "foreign_id": "7digital-US:track:29060435", "album_name": "Now That's What I Call Music! 46", "id": "TRTBTGC13EA85D33D7"}, {"release_image": "http://artwork-cdn.7static.com/static/img/sleeveart/00/018/928/0001892851_200.jpg", "foreign_release_id": "7digital-US:release:1892851", "preview_url": "http://previews.7digital.com/clip/20497004", "catalog": "7digital-US", "foreign_id": "7digital-US:track:20497004", "id": "TRKEHJK1429AA16454"}, {"release_image": "http://artwork-cdn.7static.com/static/img/sleeveart/00/032/020/0003202046_200.jpg", "foreign_release_id": "7digital-US:release:3202046", "preview_url": "http://previews.7digital.com/clip/34034794", "catalog": "7digital-US", "foreign_id": "7digital-US:track:34034794", "id": "TRJWYOG143DA42F8C2"}], "song_hotttnesss": 0.582469, "artist_id": "ARZRYXF1187FB555CC", "id": "SOLMMTH13AAD11F376"}, {"title": "Lost Stars", "artist_name": "Adam Levine", "artist_foreign_ids": [{"catalog": "7digital-US", "foreign_id": "7digital-US:artist:2110964"}], "tracks": [{"release_image": "http://artwork-cdn.7static.com/static/img/sleeveart/00/035/937/0003593777_200.jpg", "foreign_release_id": "7digital-US:release:3593777", "preview_url": "http://previews.7digital.com/clip/37725314", "catalog": "7digital-US", "foreign_id": "7digital-US:track:37725314", "id": "TRIOFIQ1475F44ABB9"}, {"release_image": "http://artwork-cdn.7static.com/static/img/sleeveart/00/035/938/0003593834_200.jpg", "foreign_release_id": "7digital-US:release:3593834", "preview_url": "http://previews.7digital.com/clip/37725765", "catalog": "7digital-US", "foreign_id": "7digital-US:track:37725765", "id": "TRYYCYU1475F44DB99"}], "song_hotttnesss": 0.581504, "artist_id": "ARSVDDS1187FB36855", "id": "SOMMVMU146F2B49B1F"}, {"title": "Lush Life", "artist_name": "Zara Larsson", "tracks": [], "song_hotttnesss": 0.580994, "artist_id": "ARVJAER13C7A655CBB", "id": "SOYTWLU14DA09EEF66"}, {"title": "My Type", "artist_name": "Saint Motel", "artist_foreign_ids": [{"catalog": "7digital-US", "foreign_id": "7digital-US:artist:469007"}], "tracks": [{"release_image": "http://artwork-cdn.7static.com/static/img/sleeveart/00/035/937/0003593740_200.jpg", "foreign_release_id": "7digital-US:release:3593740", "preview_url": "http://previews.7digital.com/clip/37724458", "catalog": "7digital-US", "foreign_id": "7digital-US:track:37724458", "id": "TRSPNGE1475F44DA09"}], "song_hotttnesss": 0.578373, "artist_id": "AROTDBE1241B9C4EED", "id": "SOAUDVZ1412189E609"}, {"title": "My Type", "artist_name": "Saint Motel", "artist_foreign_ids": [{"catalog": "7digital-US", "foreign_id": "7digital-US:artist:469007"}], "tracks": [], "song_hotttnesss": 0.578373, "artist_id": "AROTDBE1241B9C4EED", "id": "SOIDQHU146F2AFDDF9"}, {"title": "My Type", "artist_name": "Saint Motel", "artist_foreign_ids": [{"catalog": "7digital-US", "foreign_id": "7digital-US:artist:469007"}], "tracks": [], "song_hotttnesss": 0.578373, "artist_id": "AROTDBE1241B9C4EED", "id": "SOOCDEU14E6A7B66F8"}, {"title": "Loca", "artist_name": "Vince Staples", "artist_foreign_ids": [{"catalog": "7digital-US", "foreign_id": "7digital-US:artist:1408860"}], "tracks": [], "song_hotttnesss": 0.577599, "artist_id": "ARKFMFQ13A6C1556A1", "id": "SOBFLSS14E02BE7B6F"}, {"title": "Heartbeats", "artist_name": "José González", "artist_foreign_ids": [{"catalog": "7digital-US", "foreign_id": "7digital-US:artist:12767"}], "tracks": [{"album_type": "unknown", "release_image": "http://artwork-cdn.7static.com/static/img/sleeveart/00/033/199/0003319962_200.jpg", "album_date": "2003-10", "foreign_release_id": "7digital-US:release:3319962", "preview_url": "http://previews.7digital.com/clip/35127083", "catalog": "7digital-US", "foreign_id": "7digital-US:track:35127083", "album_name": "Veneer", "id": "TRWUOKM14567EE7E7D"}, {"release_image": "http://artwork-cdn.7static.com/static/img/sleeveart/00/001/057/0000105713_200.jpg", "foreign_release_id": "7digital-US:release:105713", "preview_url": "http://previews.7digital.com/clip/2572214", "catalog": "7digital-US", "foreign_id": "7digital-US:track:2572214", "id": "TROJUEB13C6D3147DC"}], "song_hotttnesss": 0.57724, "artist_id": "ARJTUSK1187B99A4B3", "id": "SOMJHIR1460BB5D6DD"}, {"title": "Rhythm Inside", "artist_name": "Loïc Nottet", "tracks": [], "song_hotttnesss": 0.575424, "artist_id": "ARXFQGN14BEE72039C", "id": "SOBESVL14C042913AE"}, {"title": "Turn Down For What", "artist_name": "DJ Snake", "artist_foreign_ids": [{"catalog": "7digital-US", "foreign_id": "7digital-US:artist:1418050"}], "tracks": [], "song_hotttnesss": 0.575044, "artist_id": "AR22ZMN1187B9B6203", "id": "SOSUOFO1486E57C175"}, {"title": "Summertime", "artist_name": "Vince Staples", "artist_foreign_ids": [{"catalog": "7digital-US", "foreign_id": "7digital-US:artist:1408860"}], "tracks": [], "song_hotttnesss": 0.573086, "artist_id": "ARKFMFQ13A6C1556A1", "id": "SOTWBJP14E02BEEB71"}, {"title": "Animals", "artist_name": "Martin Garrix", "artist_foreign_ids": [{"catalog": "7digital-US", "foreign_id": "7digital-US:artist:1390159"}], "tracks": [], "song_hotttnesss": 0.571332, "artist_id": "ARAGGUA136E57105F8", "id": "SORCAKL1410AA13D5E"}, {"title": "Animals", "artist_name": "Martin Garrix", "artist_foreign_ids": [{"catalog": "7digital-US", "foreign_id": "7digital-US:artist:1390159"}], "tracks": [], "song_hotttnesss": 0.571332, "artist_id": "ARAGGUA136E57105F8", "id": "SOLDGXK1454A7CAF73"}, {"title": "Animals", "artist_name": "Martin Garrix", "artist_foreign_ids": [{"catalog": "7digital-US", "foreign_id": "7digital-US:artist:1390159"}], "tracks": [{"release_image": "http://artwork-cdn.7static.com/static/img/sleeveart/00/036/107/0003610724_200.jpg", "foreign_release_id": "7digital-US:release:3610724", "preview_url": "http://previews.7digital.com/clip/37870814", "catalog": "7digital-US", "foreign_id": "7digital-US:track:37870814", "id": "TRWHIRQ1475F472CF1"}], "song_hotttnesss": 0.571332, "artist_id": "ARAGGUA136E57105F8", "id": "SOLQETB142C4276EFB"}, {"title": "Animals", "artist_name": "Martin Garrix", "artist_foreign_ids": [{"catalog": "7digital-US", "foreign_id": "7digital-US:artist:1390159"}], "tracks": [{"release_image": "http://artwork-cdn.7static.com/static/img/sleeveart/00/029/722/0002972287_200.jpg", "foreign_release_id": "7digital-US:release:2972287", "preview_url": "http://previews.7digital.com/clip/31667864", "catalog": "7digital-US", "foreign_id": "7digital-US:track:31667864", "id": "TRQDJQF1418BDC0C68"}, {"release_image": "http://artwork-cdn.7static.com/static/img/sleeveart/00/032/243/0003224369_200.jpg", "foreign_release_id": "7digital-US:release:3224369", "preview_url": "http://previews.7digital.com/clip/34224998", "catalog": "7digital-US", "foreign_id": "7digital-US:track:34224998", "id": "TRZWPSO14422702511"}, {"release_image": "http://artwork-cdn.7static.com/static/img/sleeveart/00/032/243/0003224369_200.jpg", "foreign_release_id": "7digital-US:release:3224369", "preview_url": "http://previews.7digital.com/clip/34225001", "catalog": "7digital-US", "foreign_id": "7digital-US:track:34225001", "id": "TRMUHGK14422703053"}, {"release_image": "http://artwork-cdn.7static.com/static/img/sleeveart/00/032/243/0003224369_200.jpg", "foreign_release_id": "7digital-US:release:3224369", "preview_url": "http://previews.7digital.com/clip/34225003", "catalog": "7digital-US", "foreign_id": "7digital-US:track:34225003", "id": "TRWPOPZ144227032A3"}], "song_hotttnesss": 0.571332, "artist_id": "ARAGGUA136E57105F8", "id": "SOFZPWO14EB6CE5054"}, {"title": "Animals", "artist_name": "Martin Garrix", "artist_foreign_ids": [{"catalog": "7digital-US", "foreign_id": "7digital-US:artist:1390159"}], "tracks": [], "song_hotttnesss": 0.571332, "artist_id": "ARAGGUA136E57105F8", "id": "SOWFAZT14180E1D386"}, {"title": "Animals", "artist_name": "Martin Garrix", "artist_foreign_ids": [{"catalog": "7digital-US", "foreign_id": "7digital-US:artist:1390159"}], "tracks": [], "song_hotttnesss": 0.571332, "artist_id": "ARAGGUA136E57105F8", "id": "SOEDKDN14A594F13AC"}, {"title": "Animals", "artist_name": "Martin Garrix", "artist_foreign_ids": [{"catalog": "7digital-US", "foreign_id": "7digital-US:artist:1390159"}], "tracks": [], "song_hotttnesss": 0.571332, "artist_id": "ARAGGUA136E57105F8", "id": "SOHCTAV146528EB233"}, {"title": "Animals", "artist_name": "Martin Garrix", "artist_foreign_ids": [{"catalog": "7digital-US", "foreign_id": "7digital-US:artist:1390159"}], "tracks": [], "song_hotttnesss": 0.571332, "artist_id": "ARAGGUA136E57105F8", "id": "SOHLDRW146196D0241"}, {"title": "Animals", "artist_name": "Martin Garrix", "artist_foreign_ids": [{"catalog": "7digital-US", "foreign_id": "7digital-US:artist:1390159"}], "tracks": [], "song_hotttnesss": 0.571332, "artist_id": "ARAGGUA136E57105F8", "id": "SOXTYUN149CC474371"}, {"title": "Animals", "artist_name": "Martin Garrix", "artist_foreign_ids": [{"catalog": "7digital-US", "foreign_id": "7digital-US:artist:1390159"}], "tracks": [], "song_hotttnesss": 0.571332, "artist_id": "ARAGGUA136E57105F8", "id": "SOYAPHR1421B3E196F"}, {"title": "Five More Hours - Deorro x Chris Brown", "artist_name": "Deorro", "artist_foreign_ids": [{"catalog": "7digital-US", "foreign_id": "7digital-US:artist:1356962"}], "tracks": [], "song_hotttnesss": 0.570656, "artist_id": "ARSVRID139A2DB2C5B", "id": "SOJIZQI14DD92528E8"}, {"title": "Earned It (Fifty Shades Of Grey) - From The \"Fifty Shades Of Grey\" Soundtrack", "artist_name": "The Weeknd", "artist_foreign_ids": [{"catalog": "7digital-US", "foreign_id": "7digital-US:artist:1420335"}], "tracks": [], "song_hotttnesss": 0.570036, "artist_id": "ARYUDWF12F2B89BB33", "id": "SOIHVLS14A5E647AE3"}, {"title": "2 Heads", "artist_name": "Coleman Hell", "artist_foreign_ids": [{"catalog": "7digital-US", "foreign_id": "7digital-US:artist:1416469"}], "tracks": [], "song_hotttnesss": 0.568574, "artist_id": "AROUAKH1373E16F669", "id": "SOSHEIB14DE0160D86"}, {"title": "2 Heads", "artist_name": "Coleman Hell", "artist_foreign_ids": [{"catalog": "7digital-US", "foreign_id": "7digital-US:artist:1416469"}], "tracks": [], "song_hotttnesss": 0.568574, "artist_id": "AROUAKH1373E16F669", "id": "SOKZBDC14B91A9872A"}, {"title": "My Love", "artist_name": "Route 94", "artist_foreign_ids": [{"catalog": "7digital-US", "foreign_id": "7digital-US:artist:1904661"}], "tracks": [], "song_hotttnesss": 0.568563, "artist_id": "ARGBMCI13F1A00A3EB", "id": "SOEMIMO1463D111D01"}]}}